{
    "backend": "api-server-django",
    "db_name": "",
    "db_pass": "",
    "db_type": "sqlite",
    "db_user": "",
    "dbms": "1",
    "description": "generated product",
    "design": "soft-ui-dashboard",
    "docker": "1",
    "err_code": 0,
    "frontend": "react",
    "heroku": "0",
    "pattern": "fullstack",
    "pro": "0",
    "task_id": "5f3670a1-214b-456c-9787-ebcdf5c0df48",
    "task_info": "Upload Sources [0%] - 318 files",
    "task_output": "5f3670a1-214b-456c-9787-ebcdf5c0df48.zip",
    "task_result": "SUCCESS",
    "task_state": "RUNNING",
    "task_ts_end": "2024-03-22-19-36-46",
    "task_ts_start": "2024-03-22-19-36-44"
}